modified_xicor/__init__.py
modified_xicor-0.3.0.dist-info/WHEEL
modified_xicor-0.3.0.dist-info/METADATA
modified_xicor-0.3.0.dist-info/RECORD
